[
 {
    "_id": "646121b8aba0c29174d703a5",
    "name": "Asus X409JA i5",
    "description": "Description du produit : Asus X409JA i5",
    "more_description": "Description du produit : Asus X409JA i5",
    "solde_price": 19.99,
    "regular_price": 199.99,
    "categories": ["ordinateurs portables"],
    "imageUrls": [
        "Ordinateurs Portables/ASUS/Asus X409JA i5.jpg",
        "Ordinateurs Portables/ASUS/Asus X409JA i5.jpg",
        "Ordinateurs Portables/ASUS/Asus X409JA i5.jpg",
        "Ordinateurs Portables/ASUS/Asus X409JA i5.jpg"
    ],
    "isAvailable": false,
    "isBestSeller": false,
    "isNewArrival": false,
    "isFeatured": false,
    "isSpecialOffer": false,
    "availability": true,
    "currency": "EUR",
    "created_at": "2023-05-14T18:00:24.022Z",
    "__v": 0
 },
 {
    "_id": "646121b8aba0c29174d703b5",
    "name": "Asus UX431F i7",
    "description": "Description du produit : Asus UX431F i7",
    "more_description": "Description du produit : Asus UX431F i7",
    "solde_price": 19.99,
    "regular_price": 199.99,
    "categories": ["ordinateurs portables"],
    "imageUrls": [
        "Ordinateurs Portables/ASUS/Asus UX431F i7.jpg",
        "Ordinateurs Portables/ASUS/Asus UX431F i7.jpg",
        "Ordinateurs Portables/ASUS/Asus UX431F i7.jpg",
        "Ordinateurs Portables/ASUS/Asus UX431F i7.jpg"
    ],
    "isAvailable": false,
    "isBestSeller": false,
    "isNewArrival": false,
    "isFeatured": false,
    "isSpecialOffer": false,
    "availability": true,
    "currency": "EUR",
    "created_at": "2023-05-14T18:00:24.022Z",
    "__v": 0
},

{
    "_id": "646121b8aba0c29174d703c5",
    "name": "Asus ROG Strix GL703GS i7",
    "description": "Description du produit : Asus ROG Strix GL703GS i7",
    "more_description": "Description du produit : Asus ROG Strix GL703GS i7",
    "solde_price": 19.99,
    "regular_price": 199.99,
    "categories": ["ordinateurs portables"],
    "imageUrls": [
        "Ordinateurs Portables/ASUS/Asus ROG Strix GL703GS i7.jpg",
        "Ordinateurs Portables/ASUS/Asus ROG Strix GL703GS i7.jpg",
        "Ordinateurs Portables/ASUS/Asus ROG Strix GL703GS i7.jpg",
        "Ordinateurs Portables/ASUS/Asus ROG Strix GL703GS i7.jpg"
    ],
    "isAvailable": false,
    "isBestSeller": false,
    "isNewArrival": false,
    "isFeatured": false,
    "isSpecialOffer": false,
    "availability": true,
    "currency": "EUR",
    "created_at": "2023-05-14T18:00:24.022Z",
    "__v": 0
},
{
    "_id": "646121b8aba0c29174d703d5",
    "name": "Asus F413JA i7",
    "description": "Description du produit : Asus F413JA i7",
    "more_description": "Description du produit : Asus F413JA i7",
    "solde_price": 19.99,
    "regular_price": 199.99,
    "categories": ["ordinateurs portables"],
    "imageUrls": [
        "Ordinateurs Portables/ASUS/Asus F413JA i7.jpg",
        "Ordinateurs Portables/ASUS/Asus F413JA i7.jpg",
        "Ordinateurs Portables/ASUS/Asus F413JA i7.jpg",
        "Ordinateurs Portables/ASUS/Asus F413JA i7.jpg"
    ],
    "isAvailable": false,
    "isBestSeller": false,
    "isNewArrival": false,
    "isFeatured": false,
    "isSpecialOffer": false,
    "availability": true,
    "currency": "EUR",
    "created_at": "2023-05-14T18:00:24.022Z",
    "__v": 0
},
{
    "_id": "646121b8aba0c29174d703e5",
    "name": "Dell Latitude 5300 i5",
    "description": "Description du produit : Dell Latitude 5300 i5",
    "more_description": "Description du produit : Dell Latitude 5300 i5",
    "solde_price": 19.99,
    "regular_price": 199.99,
    "categories": ["ordinateurs portables"],
    "imageUrls": [
        "Ordinateurs Portables/DELL/Dell Latitude 5300 i5.jpg",
        "Ordinateurs Portables/DELL/Dell Latitude 5300 i5.jpg",
        "Ordinateurs Portables/DELL/Dell Latitude 5300 i5.jpg",
        "Ordinateurs Portables/DELL/Dell Latitude 5300 i5.jpg"
    ],
    "isAvailable": false,
    "isBestSeller": false,
    "isNewArrival": false,
    "isFeatured": false,
    "isSpecialOffer": false,
    "availability": true,
    "currency": "EUR",
    "created_at": "2023-05-14T18:00:24.022Z",
    "__v": 0
},
{
    "_id": "646121b8aba0c29174d703f5",
    "name": "Dell Latitude 7300 i5",
    "description": "Description du produit : Dell Latitude 7300 i5",
    "more_description": "Description du produit : Dell Latitude 7300 i5",
    "solde_price": 19.99,
    "regular_price": 199.99,
    "categories": ["ordinateurs portables"],
    "imageUrls": [
        "Ordinateurs Portables/DELL/Dell Latitude 7300 i5.jpg",
        "Ordinateurs Portables/DELL/Dell Latitude 7300 i5.jpg",
        "Ordinateurs Portables/DELL/Dell Latitude 7300 i5.jpg",
        "Ordinateurs Portables/DELL/Dell Latitude 7300 i5.jpg"
    ],
    "isAvailable": false,
    "isBestSeller": false,
    "isNewArrival": false,
    "isFeatured": false,
    "isSpecialOffer": false,
    "availability": true,
    "currency": "EUR",
    "created_at": "2023-05-14T18:00:24.022Z",
    "__v": 0
},

{
    "_id": "646121b8aba0c29174d703g5",
    "name": "Dell Latitude 7400 i5",
    "description": "Description du produit : Dell Latitude 7400 i5",
    "more_description": "Description du produit : Dell Latitude 7400 i5",
    "solde_price": 19.99,
    "regular_price": 199.99,
    "categories": ["ordinateurs portables"],
    "imageUrls": [
        "Ordinateurs Portables/DELL/Dell Latitude 7400 i5.jpg",
        "Ordinateurs Portables/DELL/Dell Latitude 7400 i5.jpg",
        "Ordinateurs Portables/DELL/Dell Latitude 7400 i5.jpg",
        "Ordinateurs Portables/DELL/Dell Latitude 7400 i5.jpg"
    ],
    "isAvailable": false,
    "isBestSeller": false,
    "isNewArrival": false,
    "isFeatured": false,
    "isSpecialOffer": false,
    "availability": true,
    "currency": "EUR",
    "created_at": "2023-05-14T18:00:24.022Z",
    "__v": 0
},

{
    "_id": "646121b8aba0c29174d703h5",
    "name": "Fujitsu E547 i5",
    "description": "Description du produit : Fujitsu E547 i5",
    "more_description": "Description du produit : Fujitsu E547 i5",
    "solde_price": 19.99,
    "regular_price": 199.99,
    "categories": ["ordinateurs portables"],
    "imageUrls": [
        "Ordinateurs Portables/FUJITSU/Fujitsu E547 i5.jpg",
        "Ordinateurs Portables/FUJITSU/Fujitsu E547 i5.jpg",
        "Ordinateurs Portables/FUJITSU/Fujitsu E547 i5.jpg",
        "Ordinateurs Portables/FUJITSU/Fujitsu E547 i5.jpg"
    ],
    "isAvailable": false,
    "isBestSeller": false,
    "isNewArrival": false,
    "isFeatured": false,
    "isSpecialOffer": false,
    "availability": true,
    "currency": "EUR",
    "created_at": "2023-05-14T18:00:24.022Z",
    "__v": 0
},
{
    "_id": "646121b8aba0c29174d703i5",
    "name": "Fujitsu E556 i5",
    "description": "Description du produit : Fujitsu E556 i5",
    "more_description": "Description du produit : Fujitsu E556 i5",
    "solde_price": 19.99,
    "regular_price": 199.99,
    "categories": ["ordinateurs portables"],
    "imageUrls": [
        "Ordinateurs Portables/FUJITSU/Fujitsu E556 i5.jpg",
        "Ordinateurs Portables/FUJITSU/Fujitsu E556 i5.jpg",
        "Ordinateurs Portables/FUJITSU/Fujitsu E556 i5.jpg",
        "Ordinateurs Portables/FUJITSU/Fujitsu E556 i5.jpg"
    ],
    "isAvailable": false,
    "isBestSeller": false,
    "isNewArrival": false,
    "isFeatured": false,
    "isSpecialOffer": false,
    "availability": true,
    "currency": "EUR",
    "created_at": "2023-05-14T18:00:24.022Z",
    "__v": 0
},

{
    "_id": "646121b8aba0c29174d703j5",
    "name": "Fujitsu E558 i5",
    "description": "Description du produit : Fujitsu E558 i5",
    "more_description": "Description du produit : Fujitsu E558 i5",
    "solde_price": 19.99,
    "regular_price": 199.99,
    "categories": ["ordinateurs portables"],
    "imageUrls": [
        "Ordinateurs Portables/FUJITSU/Fujitsu E558 i5.jpg",
        "Ordinateurs Portables/FUJITSU/Fujitsu E558 i5.jpg",
        "Ordinateurs Portables/FUJITSU/Fujitsu E558 i5.jpg",
        "Ordinateurs Portables/FUJITSU/Fujitsu E558 i5.jpg"
    ],
    "isAvailable": false,
    "isBestSeller": false,
    "isNewArrival": false,
    "isFeatured": false,
    "isSpecialOffer": false,
    "availability": true,
    "currency": "EUR",
    "created_at": "2023-05-14T18:00:24.022Z",
    "__v": 0
},
{
    "_id": "646121b8aba0c29174d703k5",
    "name": "Fujitsu U727 i5",
    "description": "Description du produit : Fujitsu U727 i5",
    "more_description": "Description du produit : Fujitsu U727 i5",
    "solde_price": 19.99,
    "regular_price": 199.99,
    "categories": ["ordinateurs portables"],
    "imageUrls": [
        "Ordinateurs Portables/FUJITSU/Fujitsu U727 i5.jpg",
        "Ordinateurs Portables/FUJITSU/Fujitsu U727 i5.jpg",
        "Ordinateurs Portables/FUJITSU/Fujitsu U727 i5.jpg",
        "Ordinateurs Portables/FUJITSU/Fujitsu U727 i5.jpg"
    ],
    "isAvailable": false,
    "isBestSeller": false,
    "isNewArrival": false,
    "isFeatured": false,
    "isSpecialOffer": false,
    "availability": true,
    "currency": "EUR",
    "created_at": "2023-05-14T18:00:24.022Z",
    "__v": 0
},
{
    "_id": "646121b8aba0c29174d703l5",
    "name": "Fujitsu U747 i5 6th",
    "description": "Description du produit : Fujitsu U747 i5 6th",
    "more_description": "Description du produit : Fujitsu U747 i5 6th",
    "solde_price": 19.99,
    "regular_price": 199.99,
    "categories": ["ordinateurs portables"],
    "imageUrls": [
        "Ordinateurs Portables/FUJITSU/Fujitsu U747 i5 6th.jpg",
        "Ordinateurs Portables/FUJITSU/Fujitsu U747 i5 6th.jpg",
        "Ordinateurs Portables/FUJITSU/Fujitsu U747 i5 6th.jpg",
        "Ordinateurs Portables/FUJITSU/Fujitsu U747 i5 6th.jpg"
    ],
    "isAvailable": false,
    "isBestSeller": false,
    "isNewArrival": false,
    "isFeatured": false,
    "isSpecialOffer": false,
    "availability": true,
    "currency": "EUR",
    "created_at": "2023-05-14T18:00:24.022Z",
    "__v": 0
},

    {
        "_id": "646121b8aba0c29174d703m5",
        "name": "HP Elitebook 745 G5",
        "description": "Description du produit : HP Elitebook 745 G5",
        "more_description": "Description du produit : HP Elitebook 745 G5",
        "solde_price": 19.99,
        "regular_price": 199.99,
        "categories": ["ordinateurs portables"],
        "imageUrls": [
            "Ordinateurs Portables/HP/HP Elitebook 745 G5.jpg",
            "Ordinateurs Portables/HP/HP Elitebook 745 G5.jpg",
            "Ordinateurs Portables/HP/HP Elitebook 745 G5.jpg",
            "Ordinateurs Portables/HP/HP Elitebook 745 G5.jpg"
        ],
        "isAvailable": false,
        "isBestSeller": false,
        "isNewArrival": false,
        "isFeatured": false,
        "isSpecialOffer": false,
        "availability": true,
        "currency": "EUR",
        "created_at": "2023-05-14T18:00:24.022Z",
        "__v": 0
    },
    {
        "_id": "646121b8aba0c29174d703n5",
        "name": "Lenovo Thinkpad P51 i7",
        "description": "Description du produit : Lenovo Thinkpad P51 i7",
        "more_description": "Description du produit : Lenovo Thinkpad P51 i7",
        "solde_price": 19.99,
        "regular_price": 199.99,
        "categories": ["ordinateurs portables"],
        "imageUrls": [
            "Ordinateurs Portables/LENOVO/Lenovo Thinkpad P51 i7.jpg",
            "Ordinateurs Portables/LENOVO/Lenovo Thinkpad P51 i7.jpg",
            "Ordinateurs Portables/LENOVO/Lenovo Thinkpad P51 i7.jpg",
            "Ordinateurs Portables/LENOVO/Lenovo Thinkpad P51 i7.jpg"
        ],
        "isAvailable": false,
        "isBestSeller": false,
        "isNewArrival": false,
        "isFeatured": false,
        "isSpecialOffer": false,
        "availability": true,
        "currency": "EUR",
        "created_at": "2023-05-14T18:00:24.022Z",
        "__v": 0
    },
    {
        "_id": "646121b8aba0c29174d703o5",
        "name": "MacBook Air 13 Core i5 16GB 256GB SSD",
        "description": "Description du produit : MacBook Air 13 Core i5 16GB 256GB SSD",
        "more_description": "Description du produit : MacBook Air 13 Core i5 16GB 256GB SSD",
        "solde_price": 19.99,
        "regular_price": 199.99,
        "categories": ["ordinateurs portables"],
        "imageUrls": [
            "Ordinateurs Portables/MACBOOK/MacBook Air 13 Core i5 16GB 256GB SSD.jpg",
            "Ordinateurs Portables/MACBOOK/MacBook Air 13 Core i5 16GB 256GB SSD.jpg",
            "Ordinateurs Portables/MACBOOK/MacBook Air 13 Core i5 16GB 256GB SSD.jpg",
            "Ordinateurs Portables/MACBOOK/MacBook Air 13 Core i5 16GB 256GB SSD.jpg"
        ],
        "isAvailable": false,
        "isBestSeller": false,
        "isNewArrival": false,
        "isFeatured": false,
        "isSpecialOffer": false,
        "availability": true,
        "currency": "EUR",
        "created_at": "2023-05-14T18:00:24.022Z",
        "__v": 0
    },
    {
        "_id": "646121b8aba0c29174d703p5",
        "name": "Microsoft Surface Pro 5 i7",
        "description": "Description du produit : Microsoft Surface Pro 5 i7",
        "more_description": "Description du produit : Microsoft Surface Pro 5 i7",
        "solde_price": 19.99,
        "regular_price": 199.99,
        "categories": ["ordinateurs portables"],
        "imageUrls": [
            "Ordinateurs Portables/MICROSOFT/Microsoft Surface Pro 5 i7.jpg",
            "Ordinateurs Portables/MICROSOFT/Microsoft Surface Pro 5 i7.jpg",
            "Ordinateurs Portables/MICROSOFT/Microsoft Surface Pro 5 i7.jpg",
            "Ordinateurs Portables/MICROSOFT/Microsoft Surface Pro 5 i7.jpg"
        ],
        "isAvailable": false,
        "isBestSeller": false,
        "isNewArrival": false,
        "isFeatured": false,
        "isSpecialOffer": false,
        "availability": true,
        "currency": "EUR",
        "created_at": "2023-05-14T18:00:24.022Z",
        "__v": 0
    },
    {
        "_id": "646121b8aba0c29174d703q5",
        "name": "HP Probook 450 G4 i5",
        "description": "Description du produit : HP Probook 450 G4 i5",
        "more_description": "Description du produit : HP Probook 450 G4 i5",
        "solde_price": 19.99,
        "regular_price": 199.99,
        "categories": ["ordinateurs portables"],
        "imageUrls": [
            "Ordinateurs Portables/HP/HP Probook 450 G4 i5.jpg",
            "Ordinateurs Portables/HP/HP Probook 450 G4 i5.jpg",
            "Ordinateurs Portables/HP/HP Probook 450 G4 i5.jpg",
            "Ordinateurs Portables/HP/HP Probook 450 G4 i5.jpg"
        ],
        "isAvailable": false,
        "isBestSeller": false,
        "isNewArrival": false,
        "isFeatured": false,
        "isSpecialOffer": false,
        "availability": true,
        "currency": "EUR",
        "created_at": "2023-05-14T18:00:24.022Z",
        "__v": 0
    },
    {
        "_id": "646121b8aba0c29174d703r5",
        "name": "Lenovo Thinkpad T14 G1 i5",
        "description": "Description du produit : Lenovo Thinkpad T14 G1 i5",
        "more_description": "Description du produit : Lenovo Thinkpad T14 G1 i5",
        "solde_price": 19.99,
        "regular_price": 199.99,
        "categories": ["ordinateurs portables"],
        "imageUrls": [
            "Ordinateurs Portables/LENONVO/Lenovo Thinkpad T14 G1 i5.jpg",
            "Ordinateurs Portables/LENONVO/Lenovo Thinkpad T14 G1 i5.jpg",
            "Ordinateurs Portables/LENONVO/Lenovo Thinkpad T14 G1 i5.jpg",
            "Ordinateurs Portables/LENONVO/Lenovo Thinkpad T14 G1 i5.jpg"
        ],
        "isAvailable": false,
        "isBestSeller": false,
        "isNewArrival": false,
        "isFeatured": false,
        "isSpecialOffer": false,
        "availability": true,
        "currency": "EUR",
        "created_at": "2023-05-14T18:00:24.022Z",
        "__v": 0
    },
    {
        "_id": "646121b8aba0c29174d703s5",
        "name": "MacBook Air 13 Core i7 8GB 256GB SSD",
        "description": "Description du produit : MacBook Air 13 Core i7 8GB 256GB SSD",
        "more_description": "Description du produit : MacBook Air 13 Core i7 8GB 256GB SSD",
        "solde_price": 19.99,
        "regular_price": 199.99,
        "categories": ["ordinateurs portables"],
        "imageUrls": [
            "Ordinateurs Portables/MACBOOK/MacBook Air 13 Core i7 8GB 256GB SSD.jpg",
            "Ordinateurs Portables/MACBOOK/MacBook Air 13 Core i7 8GB 256GB SSD.jpg",
            "Ordinateurs Portables/MACBOOK/MacBook Air 13 Core i7 8GB 256GB SSD.jpg",
            "Ordinateurs Portables/MACBOOK/MacBook Air 13 Core i7 8GB 256GB SSD.jpg"
        ],
        "isAvailable": false,
        "isBestSeller": false,
        "isNewArrival": false,
        "isFeatured": false,
        "isSpecialOffer": false,
        "availability": true,
        "currency": "EUR",
        "created_at": "2023-05-14T18:00:24.022Z",
        "__v": 0
    },
    {
        "_id": "646121b8aba0c29174d703t5",
        "name": "HP Zbook 14u G6 i7",
        "description": "Description du produit : HP Zbook 14u G6 i7",
        "more_description": "Description du produit : HP Zbook 14u G6 i7",
        "solde_price": 19.99,
        "regular_price": 199.99,
        "categories": ["ordinateurs portables"],
        "imageUrls": [
            "Ordinateurs Portables/HP/HP Zbook 14u G6 i7.jpg",
            "Ordinateurs Portables/HP/HP Zbook 14u G6 i7.jpg",
            "Ordinateurs Portables/HP/HP Zbook 14u G6 i7.jpg",
            "Ordinateurs Portables/HP/HP Zbook 14u G6 i7.jpg"
        ],
        "isAvailable": false,
        "isBestSeller": false,
        "isNewArrival": false,
        "isFeatured": false,
        "isSpecialOffer": false,
        "availability": true,
        "currency": "EUR",
        "created_at": "2023-05-14T18:00:24.022Z",
        "__v": 0
    },
    {
        "_id": "646121b8aba0c29174d703u5",
        "name": "Lenovo Thinkpad T14 G1 i7",
        "description": "Description du produit : Lenovo Thinkpad T14 G1 i7",
        "more_description": "Description du produit : Lenovo Thinkpad T14 G1 i7",
        "solde_price": 19.99,
        "regular_price": 199.99,
        "categories": ["ordinateurs portables"],
        "imageUrls": [
            "Ordinateurs Portables/LENOVO/Lenovo Thinkpad T14 G1 i7.jpg",
            "Ordinateurs Portables/LENOVO/Lenovo Thinkpad T14 G1 i7.jpg",
            "Ordinateurs Portables/LENOVO/Lenovo Thinkpad T14 G1 i7.jpg",
            "Ordinateurs Portables/LENOVO/Lenovo Thinkpad T14 G1 i7.jpg"
        ],
        "isAvailable": false,
        "isBestSeller": false,
        "isNewArrival": false,
        "isFeatured": false,
        "isSpecialOffer": false,
        "availability": true,
        "currency": "EUR",
        "created_at": "2023-05-14T18:00:24.022Z",
        "__v": 0
    },
    {
        "_id": "646121b8aba0c29174d703v5",
        "name": "MacBook Pro 13 Core i5 16GB 256GB SSD",
        "description": "Description du produit : MacBook Pro 13 Core i5 16GB 256GB SSD",
        "more_description": "Description du produit : MacBook Pro 13 Core i5 16GB 256GB SSD",
        "solde_price": 19.99,
        "regular_price": 199.99,
        "categories": ["ordinateurs portables"],
        "imageUrls": [
            "Ordinateurs Portables/MACBOOK/MacBook_Pro_13_Core_i5_16GB_256GB_SSD.jpg",
            "Ordinateurs Portables/MACBOOK/MacBook_Pro_13_Core_i5_16GB_256GB_SSD.jpg",
            "Ordinateurs Portables/MACBOOK/MacBook_Pro_13_Core_i5_16GB_256GB_SSD.jpg",
            "Ordinateurs Portables/MACBOOK/MacBook_Pro_13_Core_i5_16GB_256GB_SSD.jpg"
        ],
        "isAvailable": false,
        "isBestSeller": false,
        "isNewArrival": false,
        "isFeatured": false,
        "isSpecialOffer": false,
        "availability": true,
        "currency": "EUR",
        "created_at": "2023-05-14T18:00:24.022Z",
        "__v": 0
    },
    {
        "_id": "646121b8aba0c29174d703w5",
        "name": "MacBook Pro 13 Core i5 16GB 256GB SSD",
        "description": "Description du produit : MacBook Pro 13 Core i5 16GB 256GB SSD",
        "more_description": "Description du produit : MacBook Pro 13 Core i5 16GB 256GB SSD",
        "solde_price": 19.99,
        "regular_price": 199.99,
        "categories": ["ordinateurs portables"],
        "imageUrls": [
            "Ordinateurs Portables/MACBOOK/MacBook_Pro_13_Core_i5_16GB_256GB_SSD.jpg",
            "Ordinateurs Portables/MACBOOK/MacBook_Pro_13_Core_i5_16GB_256GB_SSD.jpg",
            "Ordinateurs Portables/MACBOOK/MacBook_Pro_13_Core_i5_16GB_256GB_SSD.jpg",
            "Ordinateurs Portables/MACBOOK/MacBook_Pro_13_Core_i5_16GB_256GB_SSD.jpg"
        ],
        "isAvailable": false,
        "isBestSeller": false,
        "isNewArrival": false,
        "isFeatured": false,
        "isSpecialOffer": false,
        "availability": true,
        "currency": "EUR",
        "created_at": "2023-05-14T18:00:24.022Z",
        "__v": 0
    },
    {
        "_id": "646121b8aba0c29174d703x5",
        "name": "HP ZBook 15 Fury G7 i7",
        "description": "Description du produit : HP ZBook 15 Fury G7 i7",
        "more_description": "Description du produit : HP ZBook 15 Fury G7 i7",
        "solde_price": 19.99,
        "regular_price": 199.99,
        "categories": ["ordinateurs portables"],
        "imageUrls": [
            "Ordinateurs Portables/HP/HP ZBook 15 Fury G7 i7.jpg",
            "Ordinateurs Portables/HP/HP ZBook 15 Fury G7 i7.jpg",
            "Ordinateurs Portables/HP/HP ZBook 15 Fury G7 i7.jpg",
            "Ordinateurs Portables/HP/HP ZBook 15 Fury G7 i7.jpg"
        ],
        "isAvailable": false,
        "isBestSeller": false,
        "isNewArrival": false,
        "isFeatured": false,
        "isSpecialOffer": false,
        "availability": true,
        "currency": "EUR",
        "created_at": "2023-05-14T18:00:24.022Z",
        "__v": 0
    },
    {
        "_id": "646121b8aba0c29174d703y5",
        "name": "Lenovo Thinkpad T14 G1 i7",
        "description": "Description du produit : Lenovo Thinkpad T14 G1 i7",
        "more_description": "Description du produit : Lenovo Thinkpad T14 G1 i7",
        "solde_price": 19.99,
        "regular_price": 199.99,
        "categories": ["ordinateurs portables"],
        "imageUrls": [
            "Ordinateurs Portables/LENOVO/Lenovo Thinkpad T14 G1 i7.jpg",
            "Ordinateurs Portables/LENOVO/Lenovo Thinkpad T14 G1 i7.jpg",
            "Ordinateurs Portables/LENOVO/Lenovo Thinkpad T14 G1 i7.jpg",
            "Ordinateurs Portables/LENOVO/Lenovo Thinkpad T14 G1 i7.jpg"
        ],
        "isAvailable": false,
        "isBestSeller": false,
        "isNewArrival": false,
        "isFeatured": false,
        "isSpecialOffer": false,
        "availability": true,
        "currency": "EUR",
        "created_at": "2023-05-14T18:00:24.022Z",
        "__v": 0
    },
    {
        "_id": "646121b8aba0c29174d703z5",
        "name": "MacBook Pro 15 Core i7 16GB 512GB SSD Touch Bar",
        "description": "Description du produit : MacBook Pro 15 Core i7 16GB 512GB SSD Touch Bar",
        "more_description": "Description du produit : MacBook Pro 15 Core i7 16GB 512GB SSD Touch Bar",
        "solde_price": 19.99,
        "regular_price": 199.99,
        "categories": ["ordinateurs portables"],
        "imageUrls": [
            "Ordinateurs Portables/MACBOOK/MacBook Pro 15 Core i7 16GB 512GB SSD Touch Bar.jpg",
            "Ordinateurs Portables/MACBOOK/MacBook Pro 15 Core i7 16GB 512GB SSD Touch Bar.jpg",
            "Ordinateurs Portables/MACBOOK/MacBook Pro 15 Core i7 16GB 512GB SSD Touch Bar.jpg",
            "Ordinateurs Portables/MACBOOK/MacBook Pro 15 Core i7 16GB 512GB SSD Touch Bar.jpg"
        ],
        "isAvailable": false,
        "isBestSeller": false,
        "isNewArrival": false,
        "isFeatured": false,
        "isSpecialOffer": false,
        "availability": true,
        "currency": "EUR",
        "created_at": "2023-05-14T18:00:24.022Z",
        "__v": 0
    },
    {
        "_id": "646121b8aba0c29174d70ab5",
        "name": "HP ZBook 15 G6 i7",
        "description": "Description du produit : HP ZBook 15 G6 i7",
        "more_description": "Description du produit : HP ZBook 15 G6 i7",
        "solde_price": 19.99,
        "regular_price": 199.99,
        "categories": ["ordinateurs portables"],
        "imageUrls": [
            "Ordinateurs Portables/HP/HP ZBook 15 G6 i7.jpg",
            "Ordinateurs Portables/HP/HP ZBook 15 G6 i7.jpg",
            "Ordinateurs Portables/HP/HP ZBook 15 G6 i7.jpg",
            "Ordinateurs Portables/HP/HP ZBook 15 G6 i7.jpg"
        ],
        "isAvailable": false,
        "isBestSeller": false,
        "isNewArrival": false,
        "isFeatured": false,
        "isSpecialOffer": false,
        "availability": true,
        "currency": "EUR",
        "created_at": "2023-05-14T18:00:24.022Z",
        "__v": 0
    },
    {
        "_id": "646121b8aba0c29174d70ac5",
        "name": "HP ZBook 15 Studio G4 i7",
        "description": "Description du produit : HP ZBook 15 Studio G4 i7",
        "more_description": "Description du produit : HP ZBook 15 Studio G4 i7",
        "solde_price": 19.99,
        "regular_price": 199.99,
        "categories": ["ordinateurs portables"],
        "imageUrls": [
            "Ordinateurs Portables/HP/HP ZBook 15 Studio G4 i7.jpg",
            "Ordinateurs Portables/HP/HP ZBook 15 Studio G4 i7.jpg",
            "Ordinateurs Portables/HP/HP ZBook 15 Studio G4 i7.jpg",
            "Ordinateurs Portables/HP/HP ZBook 15 Studio G4 i7.jpg"
        ],
        "isAvailable": false,
        "isBestSeller": false,
        "isNewArrival": false,
        "isFeatured": false,
        "isSpecialOffer": false,
        "availability": true,
        "currency": "EUR",
        "created_at": "2023-05-14T18:00:24.022Z",
        "__v": 0
    },
    {
        "_id": "646121b8aba0c29174d70ad5",
        "name": "Lenovo Thinkpad X390 i7",
        "description": "Description du produit : Lenovo Thinkpad X390 i7",
        "more_description": "Description du produit : Lenovo Thinkpad X390 i7",
        "solde_price": 19.99,
        "regular_price": 199.99,
        "categories": ["ordinateurs portables"],
        "imageUrls": [
            "Ordinateurs Portables/LENOVO/Lenovo Thinkpad X390 i7.jpg",
            "Ordinateurs Portables/LENOVO/Lenovo Thinkpad X390 i7.jpg",
            "Ordinateurs Portables/LENOVO/Lenovo Thinkpad X390 i7.jpg",
            "Ordinateurs Portables/LENOVO/Lenovo Thinkpad X390 i7.jpg"
        ],
        "isAvailable": false,
        "isBestSeller": false,
        "isNewArrival": false,
        "isFeatured": false,
        "isSpecialOffer": false,
        "availability": true,
        "currency": "EUR",
        "created_at": "2023-05-14T18:00:24.022Z",
        "__v": 0
    }

     ]


 

